<?xml version="1.0" encoding="UTF-8"?>
<commentinfo>
  <note>This file contains the actual data for your assignment - good luck!</note>

  <comments>
    <comment>
       <name>Kingston</name>
       <count>97</count>
    </comment>
    <comment>
       <name>Rice</name>
       <count>97</count>
    </comment>
    <comment>
       <name>Rahel</name>
       <count>95</count>
    </comment>
    <comment>
       <name>Eileen</name>
       <count>92</count>
    </comment>
    <comment>
       <name>Gigha</name>
       <count>91</count>
    </comment>
    <comment>
       <name>Aqsa</name>
       <count>91</count>
    </comment>
    <comment>
       <name>Seonaidh</name>
       <count>91</count>
    </comment>
    <comment>
       <name>Emerson</name>
       <count>88</count>
    </comment>
    <comment>
       <name>Cheyenne</name>
       <count>86</count>
    </comment>
    <comment>
       <name>Calen</name>
       <count>86</count>
    </comment>
    <comment>
       <name>Obosa</name>
       <count>83</count>
    </comment>
    <comment>
       <name>Darwyn</name>
       <count>81</count>
    </comment>
    <comment>
       <name>Marcel</name>
       <count>79</count>
    </comment>
    <comment>
       <name>Ali</name>
       <count>78</count>
    </comment>
    <comment>
       <name>Sammi</name>
       <count>73</count>
    </comment>
    <comment>
       <name>Hayleigh</name>
       <count>72</count>
    </comment>
    <comment>
       <name>Shikha</name>
       <count>70</count>
    </comment>
    <comment>
       <name>Syeda</name>
       <count>68</count>
    </comment>
    <comment>
       <name>Megan</name>
       <count>68</count>
    </comment>
    <comment>
       <name>Tegan</name>
       <count>68</count>
    </comment>
    <comment>
       <name>Kenyon</name>
       <count>66</count>
    </comment>
    <comment>
       <name>Morgan</name>
       <count>62</count>
    </comment>
    <comment>
       <name>Korey</name>
       <count>62</count>
    </comment>
    <comment>
       <name>Anjolaoluwa</name>
       <count>62</count>
    </comment>
    <comment>
       <name>Blessing</name>
       <count>57</count>
    </comment>
    <comment>
       <name>Tea</name>
       <count>57</count>
    </comment>
    <comment>
       <name>Kaylyn</name>
       <count>56</count>
    </comment>
    <comment>
       <name>Bharath</name>
       <count>50</count>
    </comment>
    <comment>
       <name>Rohit</name>
       <count>49</count>
    </comment>
    <comment>
       <name>Jane</name>
       <count>49</count>
    </comment>
    <comment>
       <name>Taniesha</name>
       <count>46</count>
    </comment>
    <comment>
       <name>Mathu</name>
       <count>45</count>
    </comment>
    <comment>
       <name>Man</name>
       <count>43</count>
    </comment>
    <comment>
       <name>Neelam</name>
       <count>43</count>
    </comment>
    <comment>
       <name>Bayli</name>
       <count>39</count>
    </comment>
    <comment>
       <name>Amberlouise</name>
       <count>36</count>
    </comment>
    <comment>
       <name>Nia</name>
       <count>35</count>
    </comment>
    <comment>
       <name>Zalfa</name>
       <count>32</count>
    </comment>
    <comment>
       <name>Meleia</name>
       <count>31</count>
    </comment>
    <comment>
       <name>Phoevos</name>
       <count>31</count>
    </comment>
    <comment>
       <name>Finlay</name>
       <count>29</count>
    </comment>
    <comment>
       <name>Neive</name>
       <count>28</count>
    </comment>
    <comment>
       <name>Sofia</name>
       <count>22</count>
    </comment>
    <comment>
       <name>Chi</name>
       <count>21</count>
    </comment>
    <comment>
       <name>Lyall</name>
       <count>21</count>
    </comment>
    <comment>
       <name>Konnor</name>
       <count>18</count>
    </comment>
    <comment>
       <name>Sajid</name>
       <count>13</count>
    </comment>
    <comment>
       <name>Capri</name>
       <count>12</count>
    </comment>
    <comment>
       <name>Elizabeth</name>
       <count>6</count>
    </comment>
    <comment>
       <name>Calla</name>
       <count>3</count>
    </comment>
  </comments>
</commentinfo>
